{
    "adobe-flash-player": {
        "cargoLocks": null,
        "date": null,
        "extract": null,
        "name": "adobe-flash-player",
        "passthru": null,
        "pinned": false,
        "src": {
            "name": null,
            "sha256": "sha256-iD96ojMB/IDeh5UBFXUzpKzb/uByHtfFdnbcAy/flsM=",
            "type": "url",
            "url": "http://web.archive.org/web/20220331041116/https://fpdownload.macromedia.com/pub/flashplayer/updaters/32/flash_player_sa_linux.x86_64.tar.gz"
        },
        "version": "20220331041116"
    },
    "alcn-repo": {
        "cargoLocks": null,
        "date": "2024-06-03",
        "extract": null,
        "name": "alcn-repo",
        "passthru": null,
        "pinned": false,
        "src": {
            "deepClone": false,
            "fetchSubmodules": false,
            "leaveDotGit": false,
            "name": null,
            "owner": "archlinuxcn",
            "repo": "repo",
            "rev": "529a6eeba6bc13bb0d4176b0c13d029f1a974a52",
            "sha256": "sha256-/3PzXw8lL8gnhi8JJdmeNp7zBkXww9MzPoMmCVEkNaY=",
            "type": "github"
        },
        "version": "529a6eeba6bc13bb0d4176b0c13d029f1a974a52"
    },
    "alist": {
        "cargoLocks": null,
        "date": null,
        "extract": null,
        "name": "alist",
        "passthru": null,
        "pinned": false,
        "src": {
            "deepClone": false,
            "fetchSubmodules": false,
            "leaveDotGit": false,
            "name": null,
            "owner": "alist-org",
            "repo": "alist",
            "rev": "v3.35.0",
            "sha256": "sha256-N9WgaPzc8cuDN7N0Ny3t6ARGla0lCluzF2Mut3Pg880=",
            "type": "github"
        },
        "version": "v3.35.0"
    },
    "apple-color-emoji": {
        "cargoLocks": null,
        "date": null,
        "extract": null,
        "name": "apple-color-emoji",
        "passthru": null,
        "pinned": false,
        "src": {
            "name": null,
            "sha256": "sha256-SG3JQLybhY/fMX+XqmB/BKhQSBB0N1VRqa+H6laVUPE=",
            "type": "url",
            "url": "https://github.com/samuelngs/apple-emoji-linux/releases/download/v17.4/AppleColorEmoji.ttf"
        },
        "version": "v17.4"
    },
    "bat-theme-catppuccin": {
        "cargoLocks": null,
        "date": "2024-04-25",
        "extract": null,
        "name": "bat-theme-catppuccin",
        "passthru": null,
        "pinned": false,
        "src": {
            "deepClone": false,
            "fetchSubmodules": false,
            "leaveDotGit": false,
            "name": null,
            "rev": "d714cc1d358ea51bfc02550dabab693f70cccea0",
            "sha256": "sha256-Q5B4NDrfCIK3UAMs94vdXnR42k4AXCqZz6sRn8bzmf4=",
            "type": "git",
            "url": "https://github.com/catppuccin/bat"
        },
        "version": "d714cc1d358ea51bfc02550dabab693f70cccea0"
    },
    "dms": {
        "cargoLocks": null,
        "date": null,
        "extract": null,
        "name": "dms",
        "passthru": null,
        "pinned": false,
        "src": {
            "deepClone": false,
            "fetchSubmodules": false,
            "leaveDotGit": false,
            "name": null,
            "owner": "anacrolix",
            "repo": "dms",
            "rev": "v1.6.0",
            "sha256": "sha256-QwRLNCXDu/dKh2o17AyASlVQPIEOX6e4kTINa2ZzZkU=",
            "type": "github"
        },
        "version": "v1.6.0"
    },
    "dnsmasq-china-list": {
        "cargoLocks": null,
        "date": "2024-06-02",
        "extract": null,
        "name": "dnsmasq-china-list",
        "passthru": null,
        "pinned": false,
        "src": {
            "deepClone": false,
            "fetchSubmodules": false,
            "leaveDotGit": false,
            "name": null,
            "owner": "felixonmars",
            "repo": "dnsmasq-china-list",
            "rev": "858cf90ecd0fa7fc32ceaebd29b1f8413ef90eaf",
            "sha256": "sha256-/163SO51HEqftAVyFJL4gQIPrTUFs6KVgSOj9CJc3DE=",
            "type": "github"
        },
        "version": "858cf90ecd0fa7fc32ceaebd29b1f8413ef90eaf"
    },
    "dt": {
        "cargoLocks": {
            "Cargo.lock": [
                "./dt-v0.7.10/Cargo.lock",
                {}
            ]
        },
        "date": null,
        "extract": null,
        "name": "dt",
        "passthru": null,
        "pinned": false,
        "src": {
            "deepClone": false,
            "fetchSubmodules": false,
            "leaveDotGit": false,
            "name": null,
            "owner": "blurgyy",
            "repo": "dt",
            "rev": "v0.7.10",
            "sha256": "sha256-guTqOmrJLow84jUG6po6nfSFGFGEIdj6nf5Rm3GcLOg=",
            "type": "github"
        },
        "version": "v0.7.10"
    },
    "fcitx5-fluent-dark-theme": {
        "cargoLocks": null,
        "date": "2024-03-30",
        "extract": null,
        "name": "fcitx5-fluent-dark-theme",
        "passthru": null,
        "pinned": false,
        "src": {
            "deepClone": false,
            "fetchSubmodules": false,
            "leaveDotGit": false,
            "name": null,
            "owner": "Reverier-Xu",
            "repo": "FluentDark-fcitx5",
            "rev": "dc98bc13e8eadabed7530a68706f0a2a0a07340e",
            "sha256": "sha256-d1Y0MUOofBxwyeoXxUzQHrngL1qnL3TMa5DhDki7Pk8=",
            "type": "github"
        },
        "version": "dc98bc13e8eadabed7530a68706f0a2a0a07340e"
    },
    "fcitx5-sogou-themes": {
        "cargoLocks": null,
        "date": "2021-08-26",
        "extract": null,
        "name": "fcitx5-sogou-themes",
        "passthru": null,
        "pinned": false,
        "src": {
            "deepClone": false,
            "fetchSubmodules": false,
            "leaveDotGit": false,
            "name": null,
            "owner": "sxqsfun",
            "repo": "fcitx5-sogou-themes",
            "rev": "fbc1e34179cb6a37f0ddb28024f9bf94f0cbd70d",
            "sha256": "sha256-+Q8VNtAFWWD0UbF9nN+7FsCpcwUIi7HFJRbTeHU3HLo=",
            "type": "github"
        },
        "version": "fbc1e34179cb6a37f0ddb28024f9bf94f0cbd70d"
    },
    "fedora-virtio-win-iso": {
        "cargoLocks": null,
        "date": null,
        "extract": null,
        "name": "fedora-virtio-win-iso",
        "passthru": null,
        "pinned": false,
        "src": {
            "name": null,
            "sha256": "sha256-69SCWGaPf3jgJu0nbCip0Z2D4CD/oICtaZENyGu8vMY=",
            "type": "url",
            "url": "https://fedorapeople.org/groups/virt/virtio-win/direct-downloads/stable-virtio/virtio-win.iso"
        },
        "version": "0.1.240-1"
    },
    "fish-plugin-catppuccin": {
        "cargoLocks": null,
        "date": "2024-05-14",
        "extract": null,
        "name": "fish-plugin-catppuccin",
        "passthru": null,
        "pinned": false,
        "src": {
            "deepClone": false,
            "fetchSubmodules": false,
            "leaveDotGit": false,
            "name": null,
            "owner": "catppuccin",
            "repo": "fish",
            "rev": "a3b9eb5eaf2171ba1359fe98f20d226c016568cf",
            "sha256": "sha256-shQxlyoauXJACoZWtRUbRMxmm10R8vOigXwjxBhG8ng=",
            "type": "github"
        },
        "version": "a3b9eb5eaf2171ba1359fe98f20d226c016568cf"
    },
    "fish-plugin-tide": {
        "cargoLocks": null,
        "date": null,
        "extract": null,
        "name": "fish-plugin-tide",
        "passthru": null,
        "pinned": false,
        "src": {
            "deepClone": false,
            "fetchSubmodules": false,
            "leaveDotGit": false,
            "name": null,
            "owner": "IlanCosman",
            "repo": "tide",
            "rev": "v6.1.1",
            "sha256": "sha256-ZyEk/WoxdX5Fr2kXRERQS1U1QHH3oVSyBQvlwYnEYyc=",
            "type": "github"
        },
        "version": "v6.1.1"
    },
    "fonts-collection": {
        "cargoLocks": null,
        "date": "2013-11-16",
        "extract": null,
        "name": "fonts-collection",
        "passthru": null,
        "pinned": false,
        "src": {
            "deepClone": false,
            "fetchSubmodules": false,
            "leaveDotGit": false,
            "name": null,
            "owner": "dolbydu",
            "repo": "font",
            "rev": "f12fd1af32fdcce6e7703f457029a9c6b92970c8",
            "sha256": "sha256-oeGC4rBtI1GKdC5gKiuRjKLU9RHksyKE+a8hRV0SVXw=",
            "type": "github"
        },
        "version": "f12fd1af32fdcce6e7703f457029a9c6b92970c8"
    },
    "foot-theme-catppuccin": {
        "cargoLocks": null,
        "date": "2024-05-02",
        "extract": null,
        "name": "foot-theme-catppuccin",
        "passthru": null,
        "pinned": false,
        "src": {
            "deepClone": false,
            "fetchSubmodules": false,
            "leaveDotGit": false,
            "name": null,
            "rev": "307611230661b7b1787feb7f9d122e851bae97e9",
            "sha256": "sha256-mkPYHDJtfdfDnqLr1YOjaBpn4lCceok36LrnkUkNIE4=",
            "type": "git",
            "url": "https://github.com/catppuccin/foot"
        },
        "version": "307611230661b7b1787feb7f9d122e851bae97e9"
    },
    "gdb-dashboard": {
        "cargoLocks": null,
        "date": null,
        "extract": null,
        "name": "gdb-dashboard",
        "passthru": null,
        "pinned": false,
        "src": {
            "deepClone": false,
            "fetchSubmodules": false,
            "leaveDotGit": false,
            "name": null,
            "owner": "cyrus-and",
            "repo": "gdb-dashboard",
            "rev": "v0.17.2",
            "sha256": "sha256-UGHiYroUdqCr+a3ZgR1qKXQ3fiy2aQ5qo8gXefF9XDg=",
            "type": "github"
        },
        "version": "v0.17.2"
    },
    "gsfonts": {
        "cargoLocks": null,
        "date": null,
        "extract": null,
        "name": "gsfonts",
        "passthru": null,
        "pinned": false,
        "src": {
            "deepClone": false,
            "fetchSubmodules": false,
            "leaveDotGit": false,
            "name": null,
            "owner": "ArtifexSoftware",
            "repo": "urw-base35-fonts",
            "rev": "20200910",
            "sha256": "sha256-YQl5IDtodcbTV3D6vtJi7CwxVtHHl58fG6qCAoSaP4U=",
            "type": "github"
        },
        "version": "20200910"
    },
    "harmonyos-sans": {
        "cargoLocks": null,
        "date": "2022-05-28",
        "extract": null,
        "name": "harmonyos-sans",
        "passthru": null,
        "pinned": false,
        "src": {
            "deepClone": false,
            "fetchSubmodules": false,
            "leaveDotGit": false,
            "name": null,
            "rev": "0d79cad76b37ba0f3ccb1323c83833c78e0860de",
            "sha256": "sha256-0jIaSp3WJ9jiTFS9nhwUo27N8WWne/yW9Y8vQ+sgHoI=",
            "type": "git",
            "url": "https://gitee.com/openharmony/resources"
        },
        "version": "0d79cad76b37ba0f3ccb1323c83833c78e0860de"
    },
    "imgviz": {
        "cargoLocks": null,
        "date": null,
        "extract": null,
        "name": "imgviz",
        "passthru": null,
        "pinned": false,
        "src": {
            "name": null,
            "sha256": "sha256-2tiIaKpFDesQXgjDidPMf/1PYsx7wwiF4zzji6KRmok=",
            "type": "url",
            "url": "https://pypi.org/packages/source/i/imgviz/imgviz-1.7.5.tar.gz"
        },
        "version": "1.7.5"
    },
    "import-ply-as-verts-for-blender": {
        "cargoLocks": null,
        "date": null,
        "extract": null,
        "name": "import-ply-as-verts-for-blender",
        "passthru": null,
        "pinned": false,
        "src": {
            "deepClone": false,
            "fetchSubmodules": false,
            "leaveDotGit": false,
            "name": null,
            "owner": "TombstoneTumbleweedArt",
            "repo": "import-ply-as-verts",
            "rev": "v3.0",
            "sha256": "sha256-GzRrcJwqC78jNKkGIz5JjXtMXsPLb2jclYsubf5VB6g=",
            "type": "github"
        },
        "version": "v3.0"
    },
    "labelme": {
        "cargoLocks": null,
        "date": null,
        "extract": null,
        "name": "labelme",
        "passthru": null,
        "pinned": false,
        "src": {
            "name": null,
            "sha256": "sha256-qjSnHV8fVWHEzAtD4eZhknYpE87RLxNI4swqEvraRC4=",
            "type": "url",
            "url": "https://pypi.org/packages/source/l/labelme/labelme-5.4.1.tar.gz"
        },
        "version": "5.4.1"
    },
    "libime-history-merge": {
        "cargoLocks": {
            "Cargo.lock": [
                "./libime-history-merge-v0.3.0/Cargo.lock",
                {}
            ]
        },
        "date": null,
        "extract": null,
        "name": "libime-history-merge",
        "passthru": null,
        "pinned": false,
        "src": {
            "deepClone": false,
            "fetchSubmodules": false,
            "leaveDotGit": false,
            "name": null,
            "owner": "blurgyy",
            "repo": "libime-history-merge",
            "rev": "v0.3.0",
            "sha256": "sha256-aq8wRW+YFNNM1y6QzZzJDpisMJieURXjbKVoiRgtryE=",
            "type": "github"
        },
        "version": "v0.3.0"
    },
    "loyalsoldier-geoip": {
        "cargoLocks": null,
        "date": null,
        "extract": null,
        "name": "loyalsoldier-geoip",
        "passthru": null,
        "pinned": false,
        "src": {
            "name": null,
            "sha256": "sha256-fVLR0UmlIuyifMwN7gzd96MUli5ND7LRMrJqXjFG7As=",
            "type": "url",
            "url": "https://github.com/Loyalsoldier/v2ray-rules-dat/releases/download/202406022209/geoip.dat"
        },
        "version": "202406022209"
    },
    "loyalsoldier-geosite": {
        "cargoLocks": null,
        "date": null,
        "extract": null,
        "name": "loyalsoldier-geosite",
        "passthru": null,
        "pinned": false,
        "src": {
            "name": null,
            "sha256": "sha256-UzD1ON0YeZEEWjDIUULyFU8CQXz1Oy+dYFkgW18LO78=",
            "type": "url",
            "url": "https://github.com/Loyalsoldier/v2ray-rules-dat/releases/download/202406022209/geosite.dat"
        },
        "version": "202406022209"
    },
    "luarock-dbus_proxy": {
        "cargoLocks": null,
        "date": null,
        "extract": null,
        "name": "luarock-dbus_proxy",
        "passthru": null,
        "pinned": false,
        "src": {
            "deepClone": false,
            "fetchSubmodules": false,
            "leaveDotGit": false,
            "name": null,
            "owner": "stefano-m",
            "repo": "lua-dbus_proxy",
            "rev": "v0.10.3",
            "sha256": "sha256-Yd8TN/vKiqX7NOZyy8OwOnreWS5gdyVMTAjFqoAuces=",
            "type": "github"
        },
        "version": "v0.10.3"
    },
    "mayo": {
        "cargoLocks": null,
        "date": "2024-05-20",
        "extract": null,
        "name": "mayo",
        "passthru": null,
        "pinned": false,
        "src": {
            "deepClone": false,
            "fetchSubmodules": false,
            "leaveDotGit": false,
            "name": null,
            "owner": "fougue",
            "repo": "mayo",
            "rev": "ec5d7d7590396866f2db26c85826e6c4c2b272c4",
            "sha256": "sha256-1jruBF02GysARyfu4RqavZ4kajRMqJJtbeEz1g6ihOE=",
            "type": "github"
        },
        "version": "ec5d7d7590396866f2db26c85826e6c4c2b272c4"
    },
    "nftables-geoip-db": {
        "cargoLocks": null,
        "date": null,
        "extract": null,
        "name": "nftables-geoip-db",
        "passthru": null,
        "pinned": false,
        "src": {
            "name": null,
            "sha256": "sha256-deJyxYGQ607MABsFO0MwC2n2HntBLKm7aTaj8bRggTg=",
            "type": "url",
            "url": "https://download.db-ip.com/free/dbip-country-lite-2024-06.csv.gz"
        },
        "version": "2024-06"
    },
    "primitive": {
        "cargoLocks": null,
        "date": "2020-05-03",
        "extract": null,
        "name": "primitive",
        "passthru": null,
        "pinned": false,
        "src": {
            "deepClone": false,
            "fetchSubmodules": false,
            "leaveDotGit": false,
            "name": null,
            "owner": "fogleman",
            "repo": "primitive",
            "rev": "0373c216458be1c4b40655b796a3aefedf8b7d23",
            "sha256": "sha256-stKb3tPP/pgHTfdyTmWwVj/hLjOHtFpvJxXgBhhWgPQ=",
            "type": "github"
        },
        "version": "0373c216458be1c4b40655b796a3aefedf8b7d23"
    },
    "pypipe": {
        "cargoLocks": null,
        "date": "2024-01-04",
        "extract": null,
        "name": "pypipe",
        "passthru": null,
        "pinned": false,
        "src": {
            "deepClone": false,
            "fetchSubmodules": false,
            "leaveDotGit": false,
            "name": null,
            "rev": "29f65954c67703346c20fb8de7889b6c1b4d77b2",
            "sha256": "sha256-DIYZormAS2xFvw5ydYS5rtN7InkW1jvwuMYcKMAhJi8=",
            "type": "git",
            "url": "https://github.com/bugen/pypipe"
        },
        "version": "29f65954c67703346c20fb8de7889b6c1b4d77b2"
    },
    "rssbot": {
        "cargoLocks": {
            "Cargo.lock": [
                "./rssbot-v2.0.0-alpha.11/Cargo.lock",
                {
                    "tbot-0.6.7": "sha256-gPfwPPJEYcgETvUlT9VGNOVKp19vKHu0sEuMiHaxWKs="
                }
            ]
        },
        "date": null,
        "extract": null,
        "name": "rssbot",
        "passthru": null,
        "pinned": false,
        "src": {
            "deepClone": false,
            "fetchSubmodules": false,
            "leaveDotGit": false,
            "name": null,
            "owner": "iovxw",
            "repo": "rssbot",
            "rev": "v2.0.0-alpha.11",
            "sha256": "sha256-gNCjphzJWGjdRsyytjp1l1eYqPYI3S+kpZJ/BpJl7ac=",
            "type": "github"
        },
        "version": "v2.0.0-alpha.11"
    },
    "sc-fonts": {
        "cargoLocks": null,
        "date": "2018-08-08",
        "extract": null,
        "name": "sc-fonts",
        "passthru": null,
        "pinned": false,
        "src": {
            "deepClone": false,
            "fetchSubmodules": false,
            "leaveDotGit": false,
            "name": null,
            "owner": "Haixing-Hu",
            "repo": "latex-chinese-fonts",
            "rev": "287399335ec1beb72062ce67c36eaa8bec35f386",
            "sha256": "sha256-v3pKnmEUeLwLY7Oqkvhet+wSw53qJbQOhesuYrg1qXw=",
            "type": "github"
        },
        "version": "287399335ec1beb72062ce67c36eaa8bec35f386"
    },
    "simple-icons": {
        "cargoLocks": null,
        "date": null,
        "extract": null,
        "name": "simple-icons",
        "passthru": null,
        "pinned": false,
        "src": {
            "name": null,
            "sha256": "sha256-cFRtm9/UDI8mPe/jgrbQ0kjaAGVShndxc/kf7M0Gt/w=",
            "type": "url",
            "url": "https://github.com/simple-icons/simple-icons-font/releases/download/12.1.0/simple-icons-font-12.1.0.zip"
        },
        "version": "12.1.0"
    },
    "symbols-nerd-font": {
        "cargoLocks": null,
        "date": null,
        "extract": null,
        "name": "symbols-nerd-font",
        "passthru": null,
        "pinned": false,
        "src": {
            "name": null,
            "sha256": "sha256-vFnC6nTQIqYmL/njcv3lw2zVrj+CpWeUFIns+rTwPWY=",
            "type": "url",
            "url": "https://github.com/ryanoasis/nerd-fonts/releases/download/v3.2.1/NerdFontsSymbolsOnly.zip"
        },
        "version": "v3.2.1"
    },
    "tdesktop-lily": {
        "cargoLocks": null,
        "date": null,
        "extract": null,
        "name": "tdesktop-lily",
        "passthru": null,
        "pinned": false,
        "src": {
            "deepClone": false,
            "fetchSubmodules": true,
            "leaveDotGit": false,
            "name": null,
            "owner": "telegramdesktop",
            "repo": "tdesktop",
            "rev": "v5.1.1",
            "sha256": "sha256-IO023KwkXRwNNoxOYnD5KbL1wozREG6D3feGb6AArd4=",
            "type": "github"
        },
        "version": "v5.1.1"
    },
    "telegram-send": {
        "cargoLocks": null,
        "date": null,
        "extract": null,
        "name": "telegram-send",
        "passthru": null,
        "pinned": false,
        "src": {
            "name": null,
            "sha256": "sha256-n2mrszFZjktrqKFzsV33397E7sF+NgCkPVVMU7AVBpU=",
            "type": "url",
            "url": "https://pypi.org/packages/source/t/telegram-send/telegram-send-0.37.tar.gz"
        },
        "version": "0.37"
    },
    "tinytools": {
        "cargoLocks": {
            "Cargo.lock": [
                "./tinytools-v1.1.2/Cargo.lock",
                {}
            ]
        },
        "date": null,
        "extract": null,
        "name": "tinytools",
        "passthru": null,
        "pinned": false,
        "src": {
            "deepClone": false,
            "fetchSubmodules": false,
            "leaveDotGit": false,
            "name": null,
            "owner": "blurgyy",
            "repo": "tinytools",
            "rev": "v1.1.2",
            "sha256": "sha256-OjnSbiil2zx1sT93T6nPJXg+rwZYgryiT+DrpolrW7M=",
            "type": "github"
        },
        "version": "v1.1.2"
    },
    "tmux-plugin-catppuccin": {
        "cargoLocks": null,
        "date": null,
        "extract": null,
        "name": "tmux-plugin-catppuccin",
        "passthru": null,
        "pinned": false,
        "src": {
            "deepClone": false,
            "fetchSubmodules": false,
            "leaveDotGit": false,
            "name": null,
            "owner": "catppuccin",
            "repo": "tmux",
            "rev": "e7b50832f9bc59b0b5ef5316ba2cd6f61e4e22fc",
            "sha256": "sha256-9ZfUqEKEexSh06QyR5C+tYd4tNfBi3PsA+STzUv4+/s=",
            "type": "github"
        },
        "version": "e7b50832f9bc59b0b5ef5316ba2cd6f61e4e22fc"
    },
    "tro": {
        "cargoLocks": null,
        "date": null,
        "extract": null,
        "name": "tro",
        "passthru": null,
        "pinned": false,
        "src": {
            "deepClone": false,
            "fetchSubmodules": false,
            "leaveDotGit": false,
            "name": null,
            "owner": "MichaelAquilina",
            "repo": "tro",
            "rev": "2.9.1",
            "sha256": "sha256-u/b6MJOBX1yxUZ5a2qZdrt10v1sxCtLwBBKSn0oPakM=",
            "type": "github"
        },
        "version": "2.9.1"
    },
    "v2ray-rules-dat": {
        "cargoLocks": null,
        "date": "2024-06-02",
        "extract": null,
        "name": "v2ray-rules-dat",
        "passthru": null,
        "pinned": false,
        "src": {
            "deepClone": false,
            "fetchSubmodules": false,
            "leaveDotGit": false,
            "name": null,
            "owner": "loyalsoldier",
            "repo": "v2ray-rules-dat",
            "rev": "c5f7a91f6f30f33c8a4eb46f0330a1c5816a0ced",
            "sha256": "sha256-wpQing31IKt6PYvawrr6lXP9Du/xCg9dSw+6PBpadqg=",
            "type": "github"
        },
        "version": "c5f7a91f6f30f33c8a4eb46f0330a1c5816a0ced"
    },
    "video-compare": {
        "cargoLocks": null,
        "date": null,
        "extract": null,
        "name": "video-compare",
        "passthru": null,
        "pinned": false,
        "src": {
            "deepClone": false,
            "fetchSubmodules": false,
            "leaveDotGit": false,
            "name": null,
            "owner": "pixop",
            "repo": "video-compare",
            "rev": "20240525",
            "sha256": "sha256-OcOFwIiwShQs+wjFgAz5rPDQou/ZC+FGO3ITeuCAbgQ=",
            "type": "github"
        },
        "version": "20240525"
    },
    "vim-plugin-fcitx5-ui-nvim": {
        "cargoLocks": null,
        "date": "2023-06-16",
        "extract": null,
        "name": "vim-plugin-fcitx5-ui-nvim",
        "passthru": null,
        "pinned": false,
        "src": {
            "deepClone": false,
            "fetchSubmodules": false,
            "leaveDotGit": false,
            "name": null,
            "owner": "black-desk",
            "repo": "fcitx5-ui.nvim",
            "rev": "665ecb1365639cd6c14e47f4bacd9121106025a2",
            "sha256": "sha256-FnxhCoBC8DDUlbHIi6xkIq53Nc6DVHwXD9j9LOdRzhc=",
            "type": "github"
        },
        "version": "665ecb1365639cd6c14e47f4bacd9121106025a2"
    },
    "vscode-codicons": {
        "cargoLocks": null,
        "date": null,
        "extract": null,
        "name": "vscode-codicons",
        "passthru": null,
        "pinned": false,
        "src": {
            "name": null,
            "sha256": "sha256-NgUnV1OVrXD5QO/x5D63wuxk9OafidxYYbc0INKlePA=",
            "type": "url",
            "url": "https://github.com/microsoft/vscode-codicons/releases/download/0.0.36/codicon.ttf"
        },
        "version": "0.0.36"
    },
    "wakapi": {
        "cargoLocks": null,
        "date": null,
        "extract": null,
        "name": "wakapi",
        "passthru": null,
        "pinned": false,
        "src": {
            "deepClone": false,
            "fetchSubmodules": false,
            "leaveDotGit": false,
            "name": null,
            "owner": "muety",
            "repo": "wakapi",
            "rev": "2.11.2",
            "sha256": "sha256-lBjYtb64blFUH/iW/SmC4A7nX9asokvsNKu6QVYgmZ8=",
            "type": "github"
        },
        "version": "2.11.2"
    },
    "waypoint": {
        "cargoLocks": {
            "Cargo.lock": [
                "./waypoint-702657a6c18688fed97e498a9c95771b073835cc/Cargo.lock",
                {}
            ]
        },
        "date": "2024-04-17",
        "extract": null,
        "name": "waypoint",
        "passthru": null,
        "pinned": false,
        "src": {
            "deepClone": false,
            "fetchSubmodules": false,
            "leaveDotGit": false,
            "name": null,
            "owner": "tadeokondrak",
            "repo": "waypoint",
            "rev": "702657a6c18688fed97e498a9c95771b073835cc",
            "sha256": "sha256-ZRddQzSz++MlbbFBt5b1uZeOsOijdBtd9RfQeeTbQA4=",
            "type": "github"
        },
        "version": "702657a6c18688fed97e498a9c95771b073835cc"
    },
    "wl-screenrec": {
        "cargoLocks": {
            "Cargo.lock": [
                "./wl-screenrec-v0.1.3/Cargo.lock",
                {}
            ]
        },
        "date": null,
        "extract": null,
        "name": "wl-screenrec",
        "passthru": null,
        "pinned": false,
        "src": {
            "deepClone": false,
            "fetchSubmodules": false,
            "leaveDotGit": false,
            "name": null,
            "owner": "russelltg",
            "repo": "wl-screenrec",
            "rev": "v0.1.3",
            "sha256": "sha256-ThPZPV1GyMFRu94O9WwUpXbR4gnIML26K7TyIfXZlcI=",
            "type": "github"
        },
        "version": "v0.1.3"
    },
    "xtables-addons-perl-scripts": {
        "cargoLocks": null,
        "date": null,
        "extract": null,
        "name": "xtables-addons-perl-scripts",
        "passthru": null,
        "pinned": false,
        "src": {
            "name": null,
            "sha256": "sha256-C1LfIRe6zy4y0dP5jQnb+IsnQ5BzPTlVaZsQisr58qY=",
            "type": "url",
            "url": "https://inai.de/files/xtables-addons/xtables-addons-3.26.tar.xz"
        },
        "version": "3.26"
    },
    "zellij-hirr": {
        "cargoLocks": {
            "Cargo.lock": [
                "./zellij-hirr-v0.40.1/Cargo.lock",
                {}
            ]
        },
        "date": null,
        "extract": null,
        "name": "zellij-hirr",
        "passthru": null,
        "pinned": false,
        "src": {
            "deepClone": false,
            "fetchSubmodules": false,
            "leaveDotGit": false,
            "name": null,
            "owner": "zellij-org",
            "repo": "zellij",
            "rev": "v0.40.1",
            "sha256": "sha256-n8cwsCeKWzTw/psvLL3chBr8EcwGoeKB8JeiLSLna1k=",
            "type": "github"
        },
        "version": "v0.40.1"
    }
}